stylet/__init__.py
stylet/general.py
stylet/py.typed
stylet/specific.py
stylet-0.1.0.dist-info/LICENSE
stylet-0.1.0.dist-info/METADATA
stylet-0.1.0.dist-info/WHEEL
stylet-0.1.0.dist-info/top_level.txt
stylet-0.1.0.dist-info/RECORD
