Metadata-Version: 2.1
Name: stylet
Version: 0.1.0
Summary: Statically-typed labeled-element tensors
Author-email: Koen van Walstijn <kbvw@pm.me>
Project-URL: Source, https://codeberg.org/kbvw/stylet
Classifier: Programming Language :: Python :: 3
Classifier: License :: OSI Approved :: MIT License
Classifier: Operating System :: OS Independent
Requires-Python: >=3.11
License-File: LICENSE
Requires-Dist: numpy
